torch_things/dataset.py
torch_things-0.0.7.dist-info/METADATA
torch_things-0.0.7.dist-info/WHEEL
torch_things-0.0.7.dist-info/top_level.txt
torch_things-0.0.7.dist-info/RECORD
