Metadata-Version: 2.4
Name: torch-things
Version: 0.0.7
Summary: Helpful utilities for working with PyTorch.
Project-URL: Homepage, https://github.com/dwahdany/torch-things
Project-URL: Repository, https://github.com/dwahdany/torch-things.git
Project-URL: Issues, https://github.com/dwahdany/torch-things/issues
Requires-Python: >=3.9
Requires-Dist: torch>=2
